Chrysanthemum.jpg
MANIFEST.in
README.rst
setup.py
bin/easytoolset-joke
easytoolset/__init__.py
easytoolset/command_line.py
easytoolset/text.py
easytoolset.egg-info/PKG-INFO
easytoolset.egg-info/SOURCES.txt
easytoolset.egg-info/dependency_links.txt
easytoolset.egg-info/entry_points.txt
easytoolset.egg-info/not-zip-safe
easytoolset.egg-info/requires.txt
easytoolset.egg-info/top_level.txt