Metadata-Version: 1.0
Name: easytoolset
Version: 0.9
Summary: The easy tools in the world
Home-page: http://github.com/maxis1314
Author: Daniel
Author-email: maxis1314@163.com
License: MIT
Platform: UNKNOWN
